setup.py
HarvestNetApi/__init__.py
HarvestNetApi/main.py
HarvestNetApi.egg-info/PKG-INFO
HarvestNetApi.egg-info/SOURCES.txt
HarvestNetApi.egg-info/dependency_links.txt
HarvestNetApi.egg-info/top_level.txt