Metadata-Version: 1.2
Name: HarvestNetApi
Version: 0.0.3
Summary: HarvestNet-Api
Home-page: UNKNOWN
Author: waterlily
Author-email: b1929595403@gmail.com
License: MIT License
Platform: any
Requires-Python: >=3.7.*
